README.rst
setup.cfg
setup.py
sqlalchemy_teradata/__init__.py
sqlalchemy_teradata/base.py
sqlalchemy_teradata/compiler.py
sqlalchemy_teradata/data_type_converter.py
sqlalchemy_teradata/dialect.py
sqlalchemy_teradata/requirements.py
sqlalchemy_teradata/resolver.py
sqlalchemy_teradata/restricted_words.py
sqlalchemy_teradata/types.py
sqlalchemy_teradata.egg-info/PKG-INFO
sqlalchemy_teradata.egg-info/SOURCES.txt
sqlalchemy_teradata.egg-info/dependency_links.txt
sqlalchemy_teradata.egg-info/entry_points.txt
sqlalchemy_teradata.egg-info/requires.txt
sqlalchemy_teradata.egg-info/top_level.txt
test/test_suite.py