Metadata-Version: 1.1
Name: sqlalchemy-teradata
Version: 0.9.0.dev0
Summary: Teradata dialect for SQLAlchemy
Home-page: UNKNOWN
Author: Mark Sandan
Author-email: mark.sandan@teradata.com
License: MIT
Keywords: Teradata SQLAlchemy
Platform: UNKNOWN
Classifier: Environment :: Console
Classifier: Intended Audience :: Developers
Classifier: Programming Language :: Python
Classifier: Programming Language :: Python :: 2.7
Classifier: Topic :: Database :: Front-Ends
